timeout.py
timeout.stuff-1.0.1.dist-info/DESCRIPTION.rst
timeout.stuff-1.0.1.dist-info/METADATA
timeout.stuff-1.0.1.dist-info/RECORD
timeout.stuff-1.0.1.dist-info/WHEEL
timeout.stuff-1.0.1.dist-info/metadata.json
timeout.stuff-1.0.1.dist-info/top_level.txt
