Metadata-Version: 2.0
Name: timeout.stuff
Version: 1.0.1
Summary: A small and simple library to timeout functions
Home-page: https://github.com/seemethere/timeout.of
Author: Eli Uriegas
Author-email: seemethere101@gmail.com
License: MIT
Platform: UNKNOWN
Classifier: Programming Language :: Python :: 2
Classifier: Programming Language :: Python :: 3
Classifier: Intended Audience :: Developers
Classifier: License :: OSI Approved :: MIT License
Classifier: Topic :: Software Development :: Libraries
Classifier: Topic :: Utilities
Requires-Dist: decorator
